proofweb/__init__.py
proofweb/proofweb.py
proofweb-0.0.1.dist-info/licenses/LICENSE
proofweb-0.0.1.dist-info/METADATA
proofweb-0.0.1.dist-info/WHEEL
proofweb-0.0.1.dist-info/top_level.txt
proofweb-0.0.1.dist-info/RECORD
